MANIFEST.in
README.md
dev.txt
setup.py
building/__init__.py
building/base.py
building/exceptions.py
building/graphql.py
building/v2.py
building/v3.py
building/version.txt
building.egg-info/PKG-INFO
building.egg-info/SOURCES.txt
building.egg-info/dependency_links.txt
building.egg-info/requires.txt
building.egg-info/top_level.txt